urlarchivefield
