Metadata-Version: 1.0
Name: django-urlarchivefield
Version: 0.0.8
Summary: A custom Django model field that automatically archives a URL
Home-page: https://github.com/pastpages/django-urlarchivefield
Author: Ben Welsh
Author-email: ben.welsh@gmail.com
License: MIT
Platform: UNKNOWN
